{
  "JS_CSS_DATE": 20130320,
  "kg_domain": "http://m.kugou.com",
  "src": "http://sdn.kugou.com/link.aspx?id=16632&dl=1",
  "fr": null,
  "ver": "v3",
  "rank": {
    "total": 22,
    "list": [
      {
        "rankid": 6666,
        "id": 1,
        "update_frequency": "Daily",
        "intro": "Data Source: Kugou\r\nSorting Method: Ranked by increase in song search and play volume\r\nUpdate Frequency: Daily",
        "jump_url": "",
        "jump_title": "",
        "imgurl": "https://xianshenglu.github.io/kugou/demo/shared/assets/images/rank0.png",
        "banner7url": "https://xianshenglu.github.io/kugou/demo/shared/assets/images/rank0.png",
        "isvol": 1,
        "bannerurl": "https://imge.kugou.com/mcommonbanner/{size}/20190214/20190214100333414437.jpg",
        "custom_type": 0,
        "rankname": "Kugou Rising Chart",
        "ranktype": 2
      },
      {
        "rankid": 8888,
        "id": 2,
        "update_frequency": "Daily",
        "intro": "Data Source: Kugou\r\nSorting Method: Ranked by daily total song plays",
        "jump_url": "",
        "jump_title": "",
        "imgurl": "https://xianshenglu.github.io/kugou/demo/shared/assets/images/rank1.png",
        "banner7url": "https://imge.kugou.com/mcommon/{size}/20181019/20181019122516438289.jpg",
        "isvol": 1,
        "bannerurl": "https://imge.kugou.com/mcommonbanner/{size}/20181019/20181019122517263545.jpg",
        "custom_type": 0,
        "rankname": "Kugou TOP500",
        "ranktype": 2
      },
      {
        "rankid": 23784,
        "id": 65,
        "update_frequency": "Monday",
        "intro": "Data Source: Kugou online songs\r\nSorting Method: Ranked by weekly total song search and play volume\r\nUpdate Frequency: Monday",
        "jump_url": "",
        "jump_title": "",
        "imgurl": "https://xianshenglu.github.io/kugou/demo/shared/assets/images/rank2.png",
        "banner7url": "https://imge.kugou.com/mcommon/{size}/20181019/20181019122442518606.jpg",
        "isvol": 1,
        "bannerurl": "https://imge.kugou.com/mcommonbanner/{size}/20181019/20181019122444129869.jpg",
        "custom_type": 0,
        "rankname": "Online Hit Songs Chart",
        "ranktype": 1
      },
      {
        "rankid": 24971,
        "id": 109,
        "update_frequency": "Tuesday",
        "intro": "Data Source: Kugou DJ songs\r\nSorting Method: Ranked by weekly total song search and play volume\r\nUpdate Frequency: Tuesday",
        "jump_url": "",
        "jump_title": "",
        "imgurl": "https://xianshenglu.github.io/kugou/demo/shared/assets/images/rank3.png",
        "banner7url": "https://imge.kugou.com/mcommon/{size}/20181019/20181019122333384421.jpg",
        "isvol": 1,
        "bannerurl": "https://imge.kugou.com/mcommonbanner/{size}/20181019/20181019122335144078.jpg",
        "custom_type": 0,
        "rankname": "DJ Hot Songs Chart",
        "ranktype": 1
      },
      {
        "rankid": 31308,
        "id": 35,
        "update_frequency": "Weekdays",
        "intro": "Data Source: Chinese new songs released on Kugou within one month\r\nSorting Method: Ranked by play volume, search volume and other dimensions",
        "jump_url": "",
        "jump_title": "",
        "imgurl": "https://xianshenglu.github.io/kugou/demo/shared/assets/images/rank4.png",
        "banner7url": "https://imge.kugou.com/mcommon/{size}/20181019/20181019122308789982.jpg",
        "isvol": 1,
        "bannerurl": "https://imge.kugou.com/mcommonbanner/{size}/20181019/20181019122310609161.jpg",
        "custom_type": 0,
        "rankname": "Chinese New Songs Chart",
        "ranktype": 1
      },
      {
        "rankid": 31312,
        "id": 69,
        "update_frequency": "Weekdays",
        "intro": "Data Source: Japanese new songs released on Kugou within one month\r\nSorting Method: Ranked by play volume, search volume and other dimensions",
        "jump_url": "",
        "jump_title": "",
        "imgurl": "https://xianshenglu.github.io/kugou/demo/shared/assets/images/rank5.png",
        "banner7url": "https://imge.kugou.com/mcommon/{size}/20181019/20181019122121141047.jpg",
        "isvol": 1,
        "bannerurl": "https://imge.kugou.com/mcommonbanner/{size}/20181019/20181019122124188716.jpg",
        "custom_type": 0,
        "rankname": "Japanese New Songs Chart",
        "ranktype": 1
      },
      {
        "rankid": 31313,
        "id": 39,
        "update_frequency": "Weekdays",
        "intro": "Data Source: Cantonese new songs released on Kugou within six months\r\nSorting Method: Ranked by play volume, search volume and other dimensions",
        "jump_url": "",
        "jump_title": "",
        "imgurl": "https://xianshenglu.github.io/kugou/demo/shared/assets/images/rank6.png",
        "banner7url": "https://imge.kugou.com/mcommon/{size}/20181019/20181019122018837980.jpg",
        "isvol": 1,
        "bannerurl": "https://imge.kugou.com/mcommonbanner/{size}/20181019/20181019122021568840.jpg",
        "custom_type": 0,
        "rankname": "Cantonese New Songs Chart",
        "ranktype": 1
      },
      {
        "rankid": 21101,
        "id": 30,
        "update_frequency": "Tuesday",
        "intro": "Data Source: Kugou\r\nSorting Method: Ranked by Kugou users' shares, forwards, and downloads",
        "jump_url": "",
        "jump_title": "",
        "imgurl": "https://xianshenglu.github.io/kugou/demo/shared/assets/images/rank7.png",
        "banner7url": "https://imge.kugou.com/mcommon/{size}/20181019/20181019121858279252.jpg",
        "isvol": 1,
        "bannerurl": "https://imge.kugou.com/mcommonbanner/{size}/20181019/20181019121900772347.jpg",
        "custom_type": 0,
        "rankname": "Kugou Share Chart",
        "ranktype": 1
      },
      {
        "rankid": 30972,
        "id": 167,
        "update_frequency": "Wednesday",
        "intro": "Data Source: Tencent Original Music\r\nSorting Method: Ranked by play volume, topic popularity and other dimensions",
        "jump_url": "",
        "jump_title": "",
        "imgurl": "https://xianshenglu.github.io/kugou/demo/shared/assets/images/rank8.png",
        "banner7url": "https://imge.kugou.com/mcommon/{size}/20181019/20181019121834504050.jpg",
        "isvol": 1,
        "bannerurl": "https://imge.kugou.com/mcommonbanner/{size}/20181019/20181019121837520412.jpg",
        "custom_type": 0,
        "rankname": "Tencent Musicians Original Chart",
        "ranktype": 1
      },
      {
        "rankid": 22603,
        "id": 42,
        "update_frequency": "Monday",
        "intro": "Data Source: 5sing\r\nSorting Method: Ranked by total support cards received on 5sing per week\r\nUpdate Frequency: Monday",
        "jump_url": "",
        "jump_title": "",
        "imgurl": "https://xianshenglu.github.io/kugou/demo/shared/assets/images/rank9.png",
        "banner7url": "https://imge.kugou.com/mcommon/{size}/20181019/20181019121805248654.jpg",
        "isvol": 1,
        "bannerurl": "https://imge.kugou.com/mcommonbanner/{size}/20181019/20181019121807146762.jpg",
        "custom_type": 0,
        "rankname": "5sing Music Rank",
        "ranktype": 1
      }
    ]
  },
  "__Tpl": "rank/list.html"
}
